pagidantic/__init__.py
pagidantic/dict.py
pagidantic/factory.py
pagidantic/page.py
pagidantic/pagidantic.py
pagidantic/paginator.py
pagidantic/py.typed
pagidantic/set.py
pagidantic-2.0.0.dist-info/METADATA
pagidantic-2.0.0.dist-info/WHEEL
pagidantic-2.0.0.dist-info/licenses/LICENSE
pagidantic-2.0.0.dist-info/RECORD
