Metadata-Version: 2.1
Name: pagidantic
Version: 2.0.0
Summary: Pagination using Pydantic. Easy to use, lightweight, and easy to integrate with existing projects.
Project-URL: Homepage, https://github.com/yezz123/pagidantic
Project-URL: Funding, https://github.com/sponsors/yezz123
Author-email: Yasser Tahiri <hello@yezz.me>
License-Expression: MIT
License-File: LICENSE
Classifier: Development Status :: 5 - Production/Stable
Classifier: Framework :: Pydantic
Classifier: Framework :: Pydantic :: 2
Classifier: Intended Audience :: Developers
Classifier: License :: OSI Approved :: MIT License
Classifier: Operating System :: OS Independent
Classifier: Programming Language :: Python
Classifier: Programming Language :: Python :: 3 :: Only
Classifier: Programming Language :: Python :: 3.9
Classifier: Programming Language :: Python :: 3.10
Classifier: Programming Language :: Python :: 3.11
Classifier: Programming Language :: Python :: 3.12
Classifier: Topic :: Internet :: WWW/HTTP :: Session
Classifier: Typing :: Typed
Requires-Python: >=3.9
Requires-Dist: pydantic<2.5.4,>=2.0.0
Requires-Dist: typing-extensions<4.10.0,>=3.7.4
Provides-Extra: lint
Requires-Dist: mypy==1.8.0; extra == 'lint'
Requires-Dist: pre-commit==3.6.0; extra == 'lint'
Requires-Dist: ruff==0.1.14; extra == 'lint'
Provides-Extra: test
Requires-Dist: pytest-asyncio==0.23.3; extra == 'test'
Requires-Dist: pytest-cov==4.1.0; extra == 'test'
Requires-Dist: pytest==7.4.4; extra == 'test'
